django_amp_renderer/__init__.py
django_amp_renderer/middleware.py
tests/__init__.py
tests/test_middleware.py
django_amp_renderer-2.0.1.dist-info/LICENSE
django_amp_renderer-2.0.1.dist-info/METADATA
django_amp_renderer-2.0.1.dist-info/WHEEL
django_amp_renderer-2.0.1.dist-info/top_level.txt
django_amp_renderer-2.0.1.dist-info/RECORD
