Metadata-Version: 2.1
Name: django-amp-renderer
Version: 2.0.1
Summary: Middleware for applying AMP Renderer to the output of a request in Django.
Home-page: https://github.com/chasefinch/django-amp-renderer
Author: Chase Finch
Author-email: chase@finch.email
License: UNKNOWN
Keywords: Django,AMP,AMP Optimizer,server-side rendering
Platform: UNKNOWN
Classifier: Programming Language :: Python :: 3
Classifier: Programming Language :: Python :: 3.6
Classifier: Programming Language :: Python :: 3.7
Classifier: Programming Language :: Python :: 3.8
Classifier: Programming Language :: Python :: 3.9
Classifier: License :: OSI Approved :: Apache Software License
Classifier: Operating System :: OS Independent
Requires-Python: >=3.6
License-File: LICENSE
Requires-Dist: amp-renderer (>=2.0.0)
Requires-Dist: django (>=2.2.0)
